zipline/__init__.py
zipline/client.py
zipline/color.py
zipline/enums.py
zipline/errors.py
zipline/http.py
zipline/meta.py
zipline/models.py
zipline/py.typed
zipline/utils.py
zipline/cli/__init__.py
zipline/cli/entrypoint.py
zipline/cli/sync.py
zipline/cli/commands/__init__.py
zipline/cli/commands/_handling.py
zipline/cli/commands/shorten.py
zipline/cli/commands/upload.py
zipline/cli/commands/version.py
zipline_py-0.28.0.dist-info/licenses/LICENSE
zipline_py-0.28.0.dist-info/METADATA
zipline_py-0.28.0.dist-info/WHEEL
zipline_py-0.28.0.dist-info/entry_points.txt
zipline_py-0.28.0.dist-info/top_level.txt
zipline_py-0.28.0.dist-info/RECORD
