Metadata-Version: 2.4
Name: zipline.py
Version: 0.28.0
Summary: An async wrapper for the Zipline api.
Author-email: fretgfr <fretgfr@sudomail.com>
License: Copyright 2023-present fretgfr
Project-URL: Homepage, https://github.com/fretgfr/zipline.py/
Project-URL: Documentation, https://ziplinepy.readthedocs.io/en/latest/
Project-URL: Issues, https://github.com/fretgfr/zipline.py/issues
Keywords: zipline,api wrapper
Classifier: License :: OSI Approved :: MIT License
Classifier: Programming Language :: Python
Classifier: Programming Language :: Python :: 3
Classifier: Framework :: AsyncIO
Classifier: Operating System :: OS Independent
Classifier: Topic :: Software Development :: Libraries
Classifier: Typing :: Typed
Classifier: Development Status :: 4 - Beta
Requires-Python: >=3.8
License-File: LICENSE
Requires-Dist: aiohttp<4,>=3.7.4
Provides-Extra: dev
Requires-Dist: black; extra == "dev"
Requires-Dist: isort; extra == "dev"
Requires-Dist: typing_extensions; extra == "dev"
Provides-Extra: docs
Requires-Dist: sphinx; extra == "docs"
Requires-Dist: sphinx-rtd-theme; extra == "docs"
Provides-Extra: cli
Requires-Dist: typer>=0.15.4; extra == "cli"
Dynamic: license-file
